pytifications.py
pytifications-0.0.43.dist-info/LICENSE
pytifications-0.0.43.dist-info/METADATA
pytifications-0.0.43.dist-info/WHEEL
pytifications-0.0.43.dist-info/top_level.txt
pytifications-0.0.43.dist-info/RECORD
