Metadata-Version: 2.1
Name: pytifications
Version: 0.0.43
Summary: A python package to send notifications via telegram
Author-email: Knz13 <otaviomaya@gmail.com>
Project-URL: Homepage, https://github.com/knz13/pytifications
Project-URL: Bug Tracker, https://github.com/knz13/pytifications/issues
Classifier: Programming Language :: Python :: 3
Classifier: License :: OSI Approved :: MIT License
Classifier: Operating System :: OS Independent
Requires-Python: >=3.7
License-File: LICENSE
